fls/__init__.py
fls/fls.py
fog/__init__.py
fog/fog_functions.py
ling_features/__init__.py
non_answer/__init__.py
non_answer/non_answers.py
non_answer/regex.txt
non_answer/word_lists.txt
non_answer/word_lists/deferral
non_answer/word_lists/disc_noun
non_answer/word_lists/disc_verb_no_noun
non_answer/word_lists/disc_verb_noun
non_answer/word_lists/time_deferral
tone/__init__.py
tone/get_word_lists.py
tone/tone_measure_functions.py
tone/word_lists.py
topic/__init__.py
topic/topic_functions.py
word_count/__init__.py
word_count/word_count_functions.py
ling_features-0.0.7.dist-info/LICENCE
ling_features-0.0.7.dist-info/METADATA
ling_features-0.0.7.dist-info/WHEEL
ling_features-0.0.7.dist-info/top_level.txt
ling_features-0.0.7.dist-info/RECORD
