Metadata-Version: 2.1
Name: ling-features
Version: 0.0.7
Summary: Linguistic features commonly use in research.
Home-page: https://github.com/iangow/ling_features/
Author: Ian Gow
Author-email: iandgow@gmail.com
License: UNKNOWN
Platform: UNKNOWN
Classifier: Programming Language :: Python :: 3
Classifier: License :: OSI Approved :: MIT License
Classifier: Operating System :: OS Independent
Requires-Python: >=3
Requires-Dist: nltk
Requires-Dist: pandas
